sphinx_asdf/__init__.py
sphinx_asdf/_version.py
sphinx_asdf/asdf2rst.py
sphinx_asdf/conf.py
sphinx_asdf/connections.py
sphinx_asdf/directives.py
sphinx_asdf/md2rst.py
sphinx_asdf/nodes.py
sphinx_asdf-0.4.0.dist-info/licenses/LICENSE
sphinx_asdf-0.4.0.dist-info/METADATA
sphinx_asdf-0.4.0.dist-info/WHEEL
sphinx_asdf-0.4.0.dist-info/top_level.txt
sphinx_asdf-0.4.0.dist-info/RECORD
