Metadata-Version: 2.4
Name: sphinx-asdf
Version: 0.4.0
Summary: Sphinx plugin for generating documentation from ASDF schemas
Author: The ASDF Developers
Project-URL: documentation, https://sphinx-asdf.readthedocs.io/en/stable
Project-URL: repository, https://github.com/asdf-format/sphinx-asdf
Project-URL: tracker, https://github.com/asdf-format/sphinx-asdf/issues
Classifier: Development Status :: 5 - Production/Stable
Classifier: Programming Language :: Python
Classifier: Programming Language :: Python :: 3
Requires-Python: >=3.11
License-File: LICENSE
Requires-Dist: asdf
Requires-Dist: docutils
Requires-Dist: mistune>=3
Requires-Dist: packaging
Requires-Dist: sphinx
Requires-Dist: toml
Requires-Dist: numpydoc
Requires-Dist: sphinx-automodapi
Requires-Dist: sphinxcontrib-jquery
Provides-Extra: tests
Requires-Dist: pytest; extra == "tests"
Requires-Dist: defusedxml; extra == "tests"
Dynamic: license-file
